tideploy/__init__.py
tideploy/cli.py
tideploy/main.py
tideploy/remote.py
tideploy-0.1.1.dist-info/entry_points.txt
tideploy-0.1.1.dist-info/WHEEL
tideploy-0.1.1.dist-info/METADATA
tideploy-0.1.1.dist-info/RECORD
