Metadata-Version: 2.1
Name: tideploy
Version: 0.1.1
Summary: Remote deployment using Fabric
Home-page: https://github.com/tiptenbrink/deploy
License: Apache-2.0
Author: Tip ten Brink
Author-email: 75669206+tiptenbrink@users.noreply.github.com
Requires-Python: >=3.7,<4.0
Classifier: Development Status :: 4 - Beta
Classifier: Intended Audience :: Developers
Classifier: License :: OSI Approved :: Apache Software License
Classifier: Programming Language :: Python :: 3
Classifier: Programming Language :: Python :: 3.7
Classifier: Programming Language :: Python :: 3.8
Classifier: Programming Language :: Python :: 3.9
Requires-Dist: PyYAML (>=5.1.2,<6.0.0)
Requires-Dist: fabric (>=2.5.0,<3.0.0)
Requires-Dist: paramiko (>=2.7.0,<3.0.0)
Project-URL: Repository, https://github.com/tiptenbrink/deploy
